facebook/__init__.py
facebook/facebook.py
facebookapi-0.0.1.dist-info/LICENSE
facebookapi-0.0.1.dist-info/METADATA
facebookapi-0.0.1.dist-info/WHEEL
facebookapi-0.0.1.dist-info/top_level.txt
facebookapi-0.0.1.dist-info/RECORD
