Metadata-Version: 2.1
Name: facebookapi
Version: 0.0.1
Summary: Facebook API handler.
Home-page: https://github.com/xcollantes/facebook-api
Author: Xavier
Author-email: collantes.xavier@gmail.com
License: UNKNOWN
Platform: UNKNOWN
Classifier: Programming Language :: Python :: 3
Classifier: License :: OSI Approved :: Apache Software License
Classifier: Operating System :: OS Independent
Requires-Python: >=3.6
